kipta/__init__.py
kipta/common.py
kipta/kipta.py
kipta-0.0.1.dist-info/AUTHORS.rst
kipta-0.0.1.dist-info/LICENSE
kipta-0.0.1.dist-info/METADATA
kipta-0.0.1.dist-info/WHEEL
kipta-0.0.1.dist-info/entry_points.txt
kipta-0.0.1.dist-info/top_level.txt
kipta-0.0.1.dist-info/RECORD
