Metadata-Version: 2.1
Name: kipta
Version: 0.0.1
Summary: package testing
Author-email: Dennis Mutai <dennis.mutaigeo@gmail.com>
License: MIT License
Project-URL: Homepage, https://github.com/Dmutai/kipta
Keywords: kipta
Classifier: Intended Audience :: Developers
Classifier: License :: OSI Approved :: MIT License
Classifier: Natural Language :: English
Classifier: Programming Language :: Python :: 3.8
Classifier: Programming Language :: Python :: 3.9
Classifier: Programming Language :: Python :: 3.10
Classifier: Programming Language :: Python :: 3.11
Classifier: Programming Language :: Python :: 3.12
Requires-Python: >=3.8
License-File: LICENSE
License-File: AUTHORS.rst
Requires-Dist: numpy
Provides-Extra: all
Requires-Dist: kipta[extra] ; extra == 'all'
Provides-Extra: extra
Requires-Dist: pandas ; extra == 'extra'
